django_shortcuts_ext/__init__.py
django_shortcuts_ext/shortcuts.py
django_shortcuts_ext-1.0.3.dist-info/METADATA
django_shortcuts_ext-1.0.3.dist-info/WHEEL
django_shortcuts_ext-1.0.3.dist-info/top_level.txt
django_shortcuts_ext-1.0.3.dist-info/RECORD
